MachineFailurePredict/MachineFailurePredpict.py
MachineFailurePredict/__init__.py
MachineFailurePredict-0.0.1.dist-info/METADATA
MachineFailurePredict-0.0.1.dist-info/WHEEL
MachineFailurePredict-0.0.1.dist-info/top_level.txt
MachineFailurePredict-0.0.1.dist-info/RECORD
