Metadata-Version: 2.1
Name: MachineFailurePredict
Version: 0.0.1
Summary: MachineFailurePredict
Author: YHTest
Author-email: Yihuain163@163.com
Keywords: python,Flex Flow,Machine Learning
Classifier: Development Status :: 3 - Alpha
Classifier: Intended Audience :: Education
Classifier: Programming Language :: Python :: 2
Classifier: Programming Language :: Python :: 3
Classifier: Operating System :: MacOS :: MacOS X
Classifier: Operating System :: Microsoft :: Windows
Requires-Dist: scikit-learn
Requires-Dist: pandas
Requires-Dist: seaborn
Requires-Dist: numpy
